{"cameraMode":{"drawMode":0,"name":"Shaded","section":"Shading Mode"},"sceneLighting":false,"audioPlay":false,"sceneViewState":{"m_AlwaysRefresh":true,"showFog":true,"showSkybox":false,"showFlares":true,"showImageEffects":true,"showParticleSystems":true,"showVisualEffectGraphs":true,"m_FxEnabled":true},"in2DMode":false,"pivot":{"x":255.9202423095703,"y":90.07757568359375,"z":47.28960418701172},"rotation":{"x":-0.20846937596797944,"y":0.051902513951063159,"z":-0.01107916608452797,"w":-0.9765899777412415},"size":151.40283203125,"orthographic":false}